[
    {
        "author": "jgm",
        "category": "general",
        "parent": "",
        "content": "Are there any thoughts on what real-world data blob sizes may look like?  Are there candidates for data blobs out there today in L1 call data, and how big are they?\n\nStarting to consider external storage for beacon nodes (aka blob servers) again, given the potential operational requirements for storing blobs individually for each beacon node when at scale.",
        "created_at": "2023-10-16T19:11:44.637000+00:00",
        "attachments": null
    },
    {
        "author": "barnabasbusa",
        "category": "general",
        "parent": "",
        "content": "there was some discussion in terms of interoperability in the way the blobs are stored long term, probably shove it in s3. cc \u003c@471975503859810316\u003e and \u003c@808969530608451584\u003e",
        "created_at": "2023-10-16T20:05:40.026000+00:00",
        "attachments": null
    },
    {
        "author": "barnabasbusa",
        "category": "general",
        "parent": "",
        "content": "would be cool to have something that’s would be compatible with each other’s softwares so one’s backup could be used for another’s restore.",
        "created_at": "2023-10-16T20:06:22.900000+00:00",
        "attachments": null
    },
    {
        "author": "jgm",
        "category": "general",
        "parent": "",
        "content": "Yeah, the idea for a blob server would mainly focus on the API to store and access blobs, more than the backend.  But first question is if it's even worth doing, which comes back to bandwidth and storage requirements.",
        "created_at": "2023-10-16T20:08:04.541000+00:00",
        "attachments": null
    },
    {
        "author": "p_bitfly",
        "category": "general",
        "parent": "",
        "content": "I think we already have an integration that pushes blobs to any s3 api compatible store",
        "created_at": "2023-10-16T20:10:09.055000+00:00",
        "attachments": null
    },
    {
        "author": "p_bitfly",
        "category": "general",
        "parent": "",
        "content": "\u003c@514429265001971732\u003e Has piloted the integration and should be able to provide more details on it",
        "created_at": "2023-10-16T20:10:53.879000+00:00",
        "attachments": null
    },
    {
        "author": "pk910",
        "category": "general",
        "parent": "",
        "content": "yea, I'm doing the same in dora. \nThe discussion was more related to the key names \u0026 format, so that we could use the same storage for both explorers.\nThe conclusion was that we're storing blobs to s3 in raw binary format with the versioned hash as key.",
        "created_at": "2023-10-16T20:14:01.302000+00:00",
        "attachments": null
    },
    {
        "author": "tokey1475",
        "category": "general",
        "parent": "",
        "content": "i think arbitrum is pushing very roughly 500k every 5 minutes so a ballpark might be 20k*# of arb size rollups?",
        "created_at": "2023-10-16T20:38:39.779000+00:00",
        "attachments": null
    },
    {
        "author": "ppf.",
        "category": "general",
        "parent": "",
        "content": "yep, the idea is to just store the raw blobs as value per blobVersionedHash as key in s3\n- the explorer has a config-flag for setting the \"blob-store-provider\", which is just an url-prefix which will be used to transform all blobversionedhashes on the frontend into links to the s3 for downloading the blobs\n- the \"blob-indexer\" will work independent of the explorer, no postgres or bigtable needed (intended to run close to beaconnodes and run multiple instances)\n- first implementation: https://github.com/gobitfly/eth2-beaconchain-explorer/blob/master/exporter/blobs.go (see it more as a poc, thinking of improving it by storing an index for every 1024 finalized slots)",
        "created_at": "2023-10-16T20:38:44.181000+00:00",
        "attachments": null
    },
    {
        "author": "tokey1475",
        "category": "general",
        "parent": "",
        "content": "aka \u003c100k/block i'd guess",
        "created_at": "2023-10-16T20:39:21.261000+00:00",
        "attachments": null
    },
    {
        "author": "jgm",
        "category": "general",
        "parent": "",
        "content": "There's a big difference between each blob being 1MB and each being \u003c100KB in terms of requirements, but I wonder if we need to be worrying about worst (realistic) case.",
        "created_at": "2023-10-16T20:40:20.522000+00:00",
        "attachments": null
    },
    {
        "author": "bridge-bot",
        "category": "general",
        "parent": "",
        "content": "\u003cdankrad\u003e blobs are always 128 kB though?",
        "created_at": "2023-10-16T21:27:10.249000+00:00",
        "attachments": null
    },
    {
        "author": "jgm",
        "category": "general",
        "parent": "",
        "content": "Is that a limit or all all blobs that size?",
        "created_at": "2023-10-16T21:38:33.189000+00:00",
        "attachments": null
    },
    {
        "author": "nishant0",
        "category": "general",
        "parent": "",
        "content": "All blobs will always be at that size",
        "created_at": "2023-10-16T22:32:12.746000+00:00",
        "attachments": null
    },
    {
        "author": "nishant0",
        "category": "general",
        "parent": "",
        "content": "They cant be larger or smaller",
        "created_at": "2023-10-16T22:32:30.570000+00:00",
        "attachments": null
    },
    {
        "author": "prestonvanloon",
        "category": "general",
        "parent": "",
        "content": "they are padded with zeros",
        "created_at": "2023-10-16T22:32:47.522000+00:00",
        "attachments": null
    },
    {
        "author": "prestonvanloon",
        "category": "general",
        "parent": "",
        "content": "(i think)",
        "created_at": "2023-10-16T22:32:59.748000+00:00",
        "attachments": null
    }
]