[
    {
        "author": "holdensd",
        "category": "general",
        "parent": "",
        "content": "Hello again! is the public RPC down? I've tried a few transactions and all of them fail",
        "created_at": "2025-02-06T07:43:01.293000+00:00",
        "attachments": null
    },
    {
        "author": "parithosh",
        "category": "general",
        "parent": "",
        "content": "i just used it a few mins ago, seemed fine then",
        "created_at": "2025-02-06T07:43:36.344000+00:00",
        "attachments": null
    },
    {
        "author": "parithosh",
        "category": "general",
        "parent": "",
        "content": "i just tried it and it works for me",
        "created_at": "2025-02-06T07:44:26.681000+00:00",
        "attachments": null
    },
    {
        "author": "holdensd",
        "category": "general",
        "parent": "",
        "content": "thanks! I'll check it on my side",
        "created_at": "2025-02-06T07:45:03.264000+00:00",
        "attachments": null
    },
    {
        "author": "holdensd",
        "category": "general",
        "parent": "",
        "content": "It do not know what was happening on my side but it works now 😁",
        "created_at": "2025-02-06T07:59:47.278000+00:00",
        "attachments": null
    },
    {
        "author": "holdensd",
        "category": "general",
        "parent": "",
        "content": "In relation to EIP-7002, Debaud's audit shows a medium finding \"Fee update logic can lead to DoS\". \nHaving a look at the EIP, the `update_excess_withdrawal_requests()` is only done after processing the execution block, so I guess that this is the expected behaviour and the fee is not updated after each withdrawal request, right?",
        "created_at": "2025-02-06T08:06:19.491000+00:00",
        "attachments": null
    }
]