[
    {
        "author": "poojaranjan",
        "category": "Execution Layer",
        "parent": "",
        "content": "EIPIP meeting in ~30 mins",
        "created_at": "2021-02-24T14:23:42.115000+00:00",
        "attachments": []
    },
    {
        "author": "poojaranjan",
        "category": "Execution Layer",
        "parent": "",
        "content": "Join Zoom Meeting\nhttps://us02web.zoom.us/j/82357016731?pwd=V0hLUWIvU2V2UTdUd216WHdGNFBKUT09\n\n\nMeeting ID: 823 5701 6731\nPasscode: 885372",
        "created_at": "2021-02-24T14:23:52.366000+00:00",
        "attachments": []
    },
    {
        "author": "sky.cactus",
        "category": "Execution Layer",
        "parent": "",
        "content": "\u003c@104006934562107392\u003e would be great if you could make it.  🙂",
        "created_at": "2021-02-24T15:04:29.100000+00:00",
        "attachments": []
    },
    {
        "author": "lightclient",
        "category": "Execution Layer",
        "parent": "",
        "content": "I won’t be able to make this one, apologies",
        "created_at": "2021-02-24T15:09:43.993000+00:00",
        "attachments": []
    },
    {
        "author": "purplehat.eth",
        "category": "Execution Layer",
        "parent": "",
        "content": "Hello! I read this article and was interested in learning more about becoming an EIP wrangler. https://medium.com/ethereum-cat-herders/become-an-eip-editor-337f4376bf29",
        "created_at": "2021-02-24T16:46:03.540000+00:00",
        "attachments": []
    },
    {
        "author": "sky.cactus",
        "category": "Execution Layer",
        "parent": "",
        "content": "cc \u003c@642887713246150666\u003e ☝️",
        "created_at": "2021-02-24T16:52:06.481000+00:00",
        "attachments": []
    },
    {
        "author": "sky.cactus",
        "category": "Execution Layer",
        "parent": "",
        "content": "Also, can you give me a link to ETH Cat Hearders.",
        "created_at": "2021-02-24T16:52:22.064000+00:00",
        "attachments": []
    },
    {
        "author": "poojaranjan",
        "category": "Execution Layer",
        "parent": "",
        "content": "https://discord.gg/tzYmDmF",
        "created_at": "2021-02-24T16:53:52.220000+00:00",
        "attachments": []
    },
    {
        "author": "poojaranjan",
        "category": "Execution Layer",
        "parent": "",
        "content": "Could you also join the Ethereum Cat Herders Discord and I can add you to the appropriate channel for the EIP editors discussion.",
        "created_at": "2021-02-24T16:56:11.255000+00:00",
        "attachments": []
    },
    {
        "author": "alita85",
        "category": "Execution Layer",
        "parent": "",
        "content": "My bad \u003c@301186049323958275\u003e! I slept through it, unfortunately",
        "created_at": "2021-02-24T18:23:05.419000+00:00",
        "attachments": []
    },
    {
        "author": "alita85",
        "category": "Execution Layer",
        "parent": "",
        "content": "Nevertheless I expect to have the bot at least ready for review by next meeting",
        "created_at": "2021-02-24T18:24:16.536000+00:00",
        "attachments": []
    }
]