[
    {
        "author": "ansgar.eth",
        "category": "general",
        "parent": "",
        "content": "action items from ACDE (sorry about the delay):\n- \u003c@412614104222531604\u003e confirm decision on removing named forks after Prague from the blob schedule in the genesis files. see \u003c#688075293562503241\u003e\n- clients: look into BALs metrics support, check with \u003c@564345498471759890\u003e\n- \u003c@968526635735326741\u003e look into whether EIP-2926 should be included in repricings meta EIP\n- (implicit action item) \u003c@415548822983278593\u003e merge PRs to add PFI EIPs to Glamsterdam meta EIP",
        "created_at": "2025-10-12T04:51:54.164000+00:00",
        "attachments": null
    }
]