[
  {
    "author": "acd-bot",
    "category": "general",
    "parent": "",
    "content": "**ACDT <t:1774879200:R>**\nAgenda: <https://github.com/ethereum/pm/issues/1988>\nStream: <https://youtube.com/watch?v=uT6pdBlqByI>\nZoom: <https://ethereumfoundation.zoom.us/j/88479308162?pwd=9XvtF4kjIfZ42rQrvySQLJPu9bLz7u.1>",
    "created_at": "2026-03-30T12:31:43.981000+00:00",
    "attachments": []
  },
  {
    "author": "barnabasbusa",
    "category": "general",
    "parent": "",
    "content": "**ACDT a minute ago**",
    "created_at": "2026-03-30T14:01:19.511000+00:00",
    "attachments": []
  }
]