[
    {
        "author": "mariusvanderwijden",
        "category": "Channel Graveyard",
        "parent": "",
        "content": "I came across this today: https://www.youtube.com/watch?v=9yjZpBq1XBE (It's a bit off-topic but it explains the fast-pass queuing mechanism used in theme parks)",
        "created_at": "2022-07-20T10:48:46.304000+00:00",
        "attachments": []
    },
    {
        "author": "mariusvanderwijden",
        "category": "Channel Graveyard",
        "parent": "",
        "content": "(interesting part starts at 1h+)",
        "created_at": "2022-07-20T10:50:28.937000+00:00",
        "attachments": []
    },
    {
        "author": "trent_vanepps",
        "category": "Channel Graveyard",
        "parent": "",
        "content": "Ceremony Call tomorrow July 21 11:30 UTC\n\nJoin: https://ethereumfoundation.zoom.us/j/84584961070?pwd=M1ozNkIxQXlESTN3TWlVWS9kMTBEZz09\n\nAgenda: https://github.com/ethereum/pm/issues/569",
        "created_at": "2022-07-20T18:25:28.787000+00:00",
        "attachments": []
    }
]