[
  {
    "author": "aarshshahoffchain",
    "category": "Consensus Layer",
    "parent": "",
    "content": "<@1000001410538151996> \n\n\"Seeing that most of the times, cells \"win the race\" as per marcos dashboard, we also do not survive only because of those nodes\nI fear that for pure partial messages networks we have to stick to local devnets and simulations\"\n\nPlease can you elaborate on what you mean ? What do you mean cells \"win the race\" and \"we also do not survive only because of those nodes\" ?",
    "created_at": "2026-04-27T08:08:49.976000+00:00",
    "attachments": []
  }
]