[
  {
    "author": "nc1234",
    "category": "Cross-layer",
    "parent": "",
    "content": "> Adding a new contract with pending audit and review/improvement loops will take some time\nI am not sure how much time it takes to audit the contract (I have zero knowledge about this), but afaik it should be very similar to 7002 contracts. Also arguably, the spec is simplified nicely, no more validator and builder flow clustered together, and a lot of `if (builder) do this elif (validator) do this` statements are removed.",
    "created_at": "2026-06-12T00:21:07.161000+00:00",
    "attachments": []
  },
  {
    "author": "pk910",
    "category": "Cross-layer",
    "parent": "",
    "content": "well,  the proposed contract is written in solidity, not asm and reusing the queue logic.  So I'd threat that as a completely new audit  of a new codebase.. But might be wrong",
    "created_at": "2026-06-12T00:22:26.232000+00:00",
    "attachments": []
  },
  {
    "author": "nc1234",
    "category": "Cross-layer",
    "parent": "",
    "content": "https://github.com/ethereum/EIPs/pull/11760 it is rewritten in eas, to align more closely with 7002 contracts.",
    "created_at": "2026-06-12T00:23:36.057000+00:00",
    "attachments": []
  },
  {
    "author": "pk910",
    "category": "Cross-layer",
    "parent": "",
    "content": "oh yea, that changed since I last saw that proposal o.O  thx for the hint",
    "created_at": "2026-06-12T00:24:25.749000+00:00",
    "attachments": []
  }
]