[
    {
        "author": "maxvoltage.",
        "category": "general",
        "parent": "",
        "content": "Hi all.  A member of our crypto youtubers family, SavageMine, is in the hospital with Covid on a ventilator.  We are currently doing a Hash-a-thon from now through the end of the weekend for his family.  If you have the means and want to, please donate or hash to the following ETH address.  0x3783c3dA84a62e8847C7E656e05FE26A4b5E41a7  If you feel like watching, we are currently on a livestream.",
        "created_at": "2021-06-25T01:48:37.376000+00:00",
        "attachments": null
    },
    {
        "author": "maxvoltage.",
        "category": "general",
        "parent": "",
        "content": "https://www.youtube.com/watch?v=2TI7G7UTHJI",
        "created_at": "2021-06-25T01:48:39.530000+00:00",
        "attachments": null
    },
    {
        "author": "sky.cactus",
        "category": "general",
        "parent": "",
        "content": "While I can appreciate your desire to help out a friend, this isn't the right discord server for soliciting donations or advertising a charity drive.  This is a research server and even the \u003c#595721451651465227\u003e channel should be focused on Ethereum research.",
        "created_at": "2021-06-25T05:16:03.255000+00:00",
        "attachments": null
    },
    {
        "author": "trent_vanepps",
        "category": "general",
        "parent": "",
        "content": "https://twitter.com/trent_vanepps/status/1408461788786552834?s=20",
        "created_at": "2021-06-25T16:28:23.341000+00:00",
        "attachments": null
    },
    {
        "author": "madeof_tin7509",
        "category": "general",
        "parent": "",
        "content": "oh my gosh, this is amazing",
        "created_at": "2021-06-25T16:29:02.028000+00:00",
        "attachments": null
    },
    {
        "author": "trent_vanepps",
        "category": "general",
        "parent": "",
        "content": "the second one kinda blew my mind, so useful\n\nalso ALT ➡️  goes forward",
        "created_at": "2021-06-25T16:33:59.119000+00:00",
        "attachments": null
    },
    {
        "author": "potuz",
        "category": "general",
        "parent": "",
        "content": "Sorry guys for the really really off-topic question, but I want to confirm the url for a geth download.  I am getting this:\nhttps://gethstore.blob.core.windows.net/builds/geth-linux-amd64-1.10.4-aa637fd3.tar.gz\nHaven't downloaded geth binaries before, and I am quite surprised by the domain-name",
        "created_at": "2021-06-25T22:04:31.212000+00:00",
        "attachments": null
    },
    {
        "author": "potuz",
        "category": "general",
        "parent": "",
        "content": "\u003c@!360491619402776577\u003e Sorry to tag you for this, but you are the only one from geth and I am in a disjunctive as to building the toolchains or not",
        "created_at": "2021-06-25T22:22:54.509000+00:00",
        "attachments": null
    },
    {
        "author": "potuz",
        "category": "general",
        "parent": "",
        "content": "can you confirm the download server is on a \"windows.net\"  domain?",
        "created_at": "2021-06-25T22:23:11.775000+00:00",
        "attachments": null
    },
    {
        "author": "mvis.79",
        "category": "general",
        "parent": "",
        "content": "\u003c@!755590043632140352\u003e  For whatever it's worth, I've downloaded from there before and haven't had any problems.",
        "created_at": "2021-06-25T22:43:48.335000+00:00",
        "attachments": null
    },
    {
        "author": "potuz",
        "category": "general",
        "parent": "",
        "content": "Thanks, but I think I may be a little paranoid, if it was any other domainame I wouldn't worry much, the downloads page link is on the github repo, but the problem is that the pgp keys nor the md5 hashes are there. So I have to trust a site that it's pointing me to a \"windows.net\"  website. This is not good. I haven't spend anytime looking for the keys on the github repo cause I'm dealing with crying children... but I think I didn't miss anything",
        "created_at": "2021-06-25T22:47:12.267000+00:00",
        "attachments": null
    },
    {
        "author": "potuz",
        "category": "general",
        "parent": "",
        "content": "At this point I'm hoping that anyone involved in the release process of geth confirms me that the domain is correct. I'll wait a little bit otherwise I'll start downloading the toolchain to build it",
        "created_at": "2021-06-25T22:48:05.521000+00:00",
        "attachments": null
    },
    {
        "author": "mariusvanderwijden",
        "category": "general",
        "parent": "",
        "content": "Yep can confirm, we're using microsoft azure to host our builds, you can look at our build pipeline here: https://github.com/ethereum/go-ethereum/blob/2d4eff21ca798bcba833dae3ae719c1d6773ed3d/build/ci.go#L419",
        "created_at": "2021-06-25T22:52:26.360000+00:00",
        "attachments": null
    },
    {
        "author": "mariusvanderwijden",
        "category": "general",
        "parent": "",
        "content": "\u003c@!755590043632140352\u003e  ^",
        "created_at": "2021-06-25T22:52:46.687000+00:00",
        "attachments": null
    },
    {
        "author": "potuz",
        "category": "general",
        "parent": "",
        "content": "Oh thanks a lot, that does it for me.",
        "created_at": "2021-06-25T22:56:22.992000+00:00",
        "attachments": null
    }
]