[
  {
    "author": "raxhvl",
    "category": "general",
    "parent": "",
    "content": "<@&595685821026271242> did something change recently? I lost my badge. I notice <@792404665068158998> lost his badge too",
    "created_at": "2026-06-01T16:57:03.077000+00:00",
    "attachments": []
  },
  {
    "author": "tmiychao",
    "category": "general",
    "parent": "",
    "content": "Added your roles but not sure what happened. Funny enough you were still epf alumni!",
    "created_at": "2026-06-01T16:58:48.441000+00:00",
    "attachments": []
  },
  {
    "author": "raxhvl",
    "category": "general",
    "parent": "",
    "content": "I suspect ef-research role has been removed.",
    "created_at": "2026-06-01T17:01:10.278000+00:00",
    "attachments": []
  },
  {
    "author": "nixo.eth",
    "category": "general",
    "parent": "",
    "content": "oh ya that's probably what happened",
    "created_at": "2026-06-01T17:11:10.621000+00:00",
    "attachments": []
  }
]