[
    {
        "author": "logarithmicrex",
        "category": "Cross-layer",
        "parent": "",
        "content": "I've gotten a little lost on terminology, specifically what we mean by \"shard\" in the context of Danksharding. Is a shard a single blob index over time (for example, shard 7 would always be the shard with index 7)? Or is it more like \"the Arbitrum shard\" where all blobs posted by Arbitrum taken together would be that shard?",
        "created_at": "2022-11-07T14:41:11.653000+00:00",
        "attachments": null
    },
    {
        "author": "bridge-bot",
        "category": "Cross-layer",
        "parent": "",
        "content": "\u003cdankrad\u003e more like the first, I think",
        "created_at": "2022-11-07T15:59:54.945000+00:00",
        "attachments": null
    },
    {
        "author": "dmitriishmatko",
        "category": "Cross-layer",
        "parent": "",
        "content": "It's not clear from the spec for me, whether we keep old `beacon_block` gossip topic and keep gossiping BeaconBlock without blobs too\n\u003e All topics remain stable except the beacon block topic which is updated with the modified type.\nso we keep old one too?\n\u003e The new topics along with the type of the data field of a gossipsub message are given in this table:\n\u003e `beacon_block_and_blobs_sidecar`",
        "created_at": "2022-11-07T17:49:25.384000+00:00",
        "attachments": null
    },
    {
        "author": "mbrain",
        "category": "Cross-layer",
        "parent": "",
        "content": "We don't know either. Need to clarify the spec.",
        "created_at": "2022-11-07T19:39:11.672000+00:00",
        "attachments": null
    },
    {
        "author": "bridge-bot",
        "category": "Cross-layer",
        "parent": "",
        "content": "\u003cinphi\u003e \u003e \u003cinphi\u003e  We discussed at the 4844 call to not keep the old topic. We no longer wanna propagate or accept virgin beacon blocks after the 4844 upgrade (re @sharded_data_bot: \u003cDmitrii Shmatko\u003e It's not clear from the spec for me, whether we keep old `beacon_block` gossip topic and keep gossiping BeaconBlock without blobs too\n\u003e All topics remain stable except the beacon block topic which is updated with the modified type.\nso we keep old one too?\n\u003e The new topics along with the type of the data field of a gossipsub message are given in this table:\n\u003e `beacon_block_and_blobs_sidecar`)",
        "created_at": "2022-11-07T21:00:11.407000+00:00",
        "attachments": null
    },
    {
        "author": "bridge-bot",
        "category": "Cross-layer",
        "parent": "",
        "content": "\u003cdankrad\u003e What is the idea for when we get full sharding? Are we going to strip it off again and go back to virgin blocks?",
        "created_at": "2022-11-07T21:01:02.513000+00:00",
        "attachments": null
    },
    {
        "author": "bridge-bot",
        "category": "Cross-layer",
        "parent": "",
        "content": "\u003cinphi\u003e We didn't think that far ahead, but I assume so. In that case, we can keep using the same topic while leaving the blobs_sidecar field unset.",
        "created_at": "2022-11-07T21:03:17.931000+00:00",
        "attachments": null
    },
    {
        "author": "bridge-bot",
        "category": "Cross-layer",
        "parent": "",
        "content": "\u003cdankrad\u003e right",
        "created_at": "2022-11-07T21:03:35.197000+00:00",
        "attachments": null
    },
    {
        "author": "bridge-bot",
        "category": "Cross-layer",
        "parent": "",
        "content": "\u003cdankrad\u003e we should probably check that the transition that way is easy as well",
        "created_at": "2022-11-07T21:03:48.700000+00:00",
        "attachments": null
    }
]