[
    {
        "author": "nflaig",
        "category": "Consensus Layer",
        "parent": "",
        "content": "Seems like Nimbus is the only client that has this flag already `--keymanager-token-file` (https://nimbus.guide/keymanager-api.html), might be hard to have the exact same flag name in all clients, as at least for Lodestar the flag would be part of `keymanager` group (not top level flag like jwt-secret). But at least the behavior of the flag should be the same, i.e. path to file, read token from that file, validate that token against what is sent in Authorization header (bearer scheme).",
        "created_at": "2024-03-09T10:31:18.519000+00:00",
        "attachments": null
    },
    {
        "author": "barnabasbusa",
        "category": "Consensus Layer",
        "parent": "",
        "content": "and the token’s format itself should be the same",
        "created_at": "2024-03-09T11:46:41.680000+00:00",
        "attachments": null
    }
]